cuik_molmaker/__init__.py
cuik_molmaker/cuik_molmaker.cpython-311-x86_64-linux-gnu.so
cuik_molmaker-0.1a1.dist-info/METADATA
cuik_molmaker-0.1a1.dist-info/WHEEL
cuik_molmaker-0.1a1.dist-info/top_level.txt
cuik_molmaker-0.1a1.dist-info/RECORD
