Metadata-Version: 2.4
Name: cuik_molmaker
Version: 0.1a1
Summary: C++ module for featurizing molecules
Author: S. Veccham
Author-email: sveccham@nvidia.com
License: Apache 2.0
Classifier: Development Status :: 3 - Alpha
Classifier: Intended Audience :: Science/Research
Classifier: License :: OSI Approved :: Apache Software License
Classifier: Programming Language :: Python :: 3.11
Classifier: Topic :: Scientific/Engineering :: Chemistry
Requires-Python: >=3.11
Requires-Dist: rdkit==2024.03.4
Requires-Dist: torch==2.6.0
Dynamic: author
Dynamic: author-email
Dynamic: classifier
Dynamic: description
Dynamic: description-content-type
Dynamic: license
Dynamic: requires-dist
Dynamic: requires-python
Dynamic: summary
